{
  "expectation_suite_name": "amazonsales_dim_product_suite",
  "expectations": [
    {
      "expectation_type": "expect_column_to_exist",
      "kwargs": {"column": "product_id"}
    },
    {
      "expectation_type": "expect_column_values_to_not_be_null",
      "kwargs": {"column": "product_id"}
    },
    {
      "expectation_type": "expect_column_values_to_be_unique",
      "kwargs": {"column": "product_id"}
    },
    {
      "expectation_type": "expect_column_values_to_not_be_null",
      "kwargs": {"column": "product_name"}
    },
    {
      "expectation_type": "expect_column_values_to_not_be_null",
      "kwargs": {"column": "category"}
    },
    {
      "expectation_type": "expect_column_value_lengths_to_be_between",
      "kwargs": {
        "column": "about_product",
        "min_value": 10
      }
    },
    {
      "expectation_type": "expect_column_values_to_match_regex",
      "kwargs": {
        "column": "img_link",
        "regex": "http[s]?://.*",
        "mostly": 0.9
      }
    },
    {
      "expectation_type": "expect_column_values_to_match_regex",
      "kwargs": {
        "column": "product_link",
        "regex": "http[s]?://.*",
        "mostly": 0.9
      }
    }
  ]
}
